[
  {
    "repository": {
      "owner": "onflow",
      "name": "flow-ft",
      "branch": "master",
      "data": [
        {
          "source": "docs/",
          "destination": "building-on-flow/token-standards/flow-ft/",
          "doCopy": true
        }
      ]
    }
  },
  {
    "repository": {
      "owner": "onflow",
      "name": "flow-nft",
      "branch": "master",
      "data": [
        {
          "source": "docs/",
          "destination": "building-on-flow/token-standards/flow-nft/",
          "doCopy": true
        }
      ]
    }
  }
]
